pylint_enums/__init__.py
pylint_enums/checker.py
pylint_enums/tests/__init__.py
pylint_enums/tests/constants.py
pylint_enums/tests/test_checker.py
pylint_enums-0.0.5.dist-info/METADATA
pylint_enums-0.0.5.dist-info/RECORD
pylint_enums-0.0.5.dist-info/WHEEL
pylint_enums-0.0.5.dist-info/top_level.txt
