Metadata-Version: 2.1
Name: pylint-enums
Version: 0.0.5
Summary: A Pylint plugin that checks for a specific implementation of Enum subclasses.
Home-page: https://github.com/cs-cordero/pylint_enums
Author: Christopher Cordero
Author-email: ccordero@protonmail.com
License: UNKNOWN
Platform: UNKNOWN
Classifier: Programming Language :: Python :: 3
Classifier: License :: OSI Approved :: MIT License
Classifier: Operating System :: OS Independent
Requires-Dist: pylint
